bytemaker/__init__.py
bytemaker/typing_redirect.py
bytemaker/utils.py
bytemaker/bittypes/__init__.py
bytemaker/bittypes/bittype.py
bytemaker/bittypes/buffer.py
bytemaker/bittypes/float.py
bytemaker/bittypes/int.py
bytemaker/bittypes/string.py
bytemaker/bitvector/__init__.py
bytemaker/bitvector/bitvector.py
bytemaker/bitvector/bitvector.pyi
bytemaker/bitvector/bitvector_with_bitarray_speedup.py
bytemaker-0.9.2.dist-info/LICENCE.md
bytemaker-0.9.2.dist-info/METADATA
bytemaker-0.9.2.dist-info/WHEEL
bytemaker-0.9.2.dist-info/top_level.txt
bytemaker-0.9.2.dist-info/RECORD
