Metadata-Version: 2.1
Name: bytemaker
Version: 0.9.2
Summary: A sub-byte-struct-supporting Python serialization/deserialization library for Python 3.8.
Author-email: "D. Estes McKnight" <contact-2@demcknight.com>
Project-URL: Homepage, https://github.com/dem1995/bytemaker
Project-URL: PyPi Page, https://pypi.org/project/bytemaker/
Classifier: Programming Language :: Python :: 3
Classifier: License :: OSI Approved :: MIT License
Classifier: Operating System :: OS Independent
Requires-Python: >=3.8
License-File: LICENCE.md
Requires-Dist: bitarray>=2.9.0
Provides-Extra: dev
Requires-Dist: pytest>=6; extra == "dev"
Requires-Dist: flake8>=3.8; extra == "dev"
Requires-Dist: pre-commit>=3.8.0; extra == "dev"
Provides-Extra: docs
Requires-Dist: Sphinx>=8.0; extra == "docs"
Requires-Dist: piccolo-theme>=0.2.3; extra == "docs"
Requires-Dist: pydata-sphinx-theme>0.15; extra == "docs"
Requires-Dist: sphinx-copybutton; extra == "docs"
Requires-Dist: sphinx-design; extra == "docs"
Provides-Extra: testing
Requires-Dist: pytest>=6; extra == "testing"
Requires-Dist: flake8>=3.8; extra == "testing"
